datarefiner_client/__init__.py
datarefiner_client/api/__init__.py
datarefiner_client/api/entities/__init__.py
datarefiner_client/api/entities/project.py
datarefiner_client/api/entities/supervised_label.py
datarefiner_client/api/entities/upload.py
datarefiner_client/api/explore.py
datarefiner_client/api/explore_exports.py
datarefiner_client/api/projects.py
datarefiner_client/api/supervised_labels.py
datarefiner_client/api/uploads.py
datarefiner_client/client.py
datarefiner_client/dataframe_uploader.py
datarefiner_client/exceptions.py
datarefiner_client/iclient.py
datarefiner_client/services/__init__.py
datarefiner_client/services/project_settings.py
datarefiner_client/settings.py
datarefiner_client/utils.py
datarefiner_client-0.0.6.dist-info/METADATA
datarefiner_client-0.0.6.dist-info/WHEEL
datarefiner_client-0.0.6.dist-info/RECORD
