Metadata-Version: 2.1
Name: datarefiner-client
Version: 0.0.6
Summary: API client for Datarefiner
Author: Datarefiner
Author-email: admin@datarefiner.com
Requires-Python: >=3.8,<4.0
Classifier: Programming Language :: Python :: 3
Classifier: Programming Language :: Python :: 3.8
Classifier: Programming Language :: Python :: 3.9
Classifier: Programming Language :: Python :: 3.10
Classifier: Programming Language :: Python :: 3.11
Classifier: Programming Language :: Python :: 3.12
Classifier: Programming Language :: Python :: 3.13
Requires-Dist: dacite (>=1.8.1,<2.0.0)
Requires-Dist: dataclasses-json (>=0.6.1,<0.7.0)
Requires-Dist: environs (>=9.5.0,<10.0.0)
Requires-Dist: pandas (>=1.4)
Requires-Dist: progressbar (>=2.5,<3.0)
Requires-Dist: requests (>=2.31.0,<3.0.0)
Requires-Dist: tenacity (>=8.2.3,<9.0.0)
Requires-Dist: tqdm (>=4.66.1,<5.0.0)
